UnityPy/UnityPyBoost.cpython-312-x86_64-linux-musl.so
UnityPy/UnityPyBoost.pyi
UnityPy/__init__.py
UnityPy/__main__.py
UnityPy/config.py
UnityPy/environment.py
UnityPy/exceptions.py
UnityPy/py.typed
UnityPy/classes/ClassIDTypeToClassMap.py
UnityPy/classes/Object.py
UnityPy/classes/PPtr.py
UnityPy/classes/UnknownObject.py
UnityPy/classes/__init__.py
UnityPy/classes/generated.py
UnityPy/classes/math.py
UnityPy/classes/legacy_patch/AudioClip.py
UnityPy/classes/legacy_patch/AudioClip.pyi
UnityPy/classes/legacy_patch/GameObject.py
UnityPy/classes/legacy_patch/GameObject.pyi
UnityPy/classes/legacy_patch/Mesh.py
UnityPy/classes/legacy_patch/Mesh.pyi
UnityPy/classes/legacy_patch/Renderer.py
UnityPy/classes/legacy_patch/Renderer.pyi
UnityPy/classes/legacy_patch/Shader.py
UnityPy/classes/legacy_patch/Shader.pyi
UnityPy/classes/legacy_patch/Sprite.py
UnityPy/classes/legacy_patch/Sprite.pyi
UnityPy/classes/legacy_patch/Texture2D.py
UnityPy/classes/legacy_patch/Texture2D.pyi
UnityPy/classes/legacy_patch/Texture2DArray.py
UnityPy/classes/legacy_patch/Texture2DArray.pyi
UnityPy/classes/legacy_patch/__init__.py
UnityPy/cli/__init__.py
UnityPy/cli/update_tpk.py
UnityPy/enums/Audio.py
UnityPy/enums/BuildTarget.py
UnityPy/enums/BundleFile.py
UnityPy/enums/ClassIDType.py
UnityPy/enums/CommonString.py
UnityPy/enums/ExtendableEnum.py
UnityPy/enums/FileType.py
UnityPy/enums/GfxPrimitiveType.py
UnityPy/enums/GraphicsFormat.py
UnityPy/enums/MeshTopology.py
UnityPy/enums/PassType.py
UnityPy/enums/SerializedPropertyType.py
UnityPy/enums/ShaderCompilerPlatform.py
UnityPy/enums/ShaderGpuProgramType.py
UnityPy/enums/SpriteMeshType.py
UnityPy/enums/SpritePackingMode.py
UnityPy/enums/SpritePackingRotation.py
UnityPy/enums/TextureDimension.py
UnityPy/enums/TextureFormat.py
UnityPy/enums/VertexFormat.py
UnityPy/enums/__init__.py
UnityPy/export/AudioClipConverter.py
UnityPy/export/MeshExporter.py
UnityPy/export/MeshRendererExporter.py
unitypy-1.24.2.dist-info/METADATA
unitypy-1.24.2.dist-info/WHEEL
unitypy-1.24.2.dist-info/entry_points.txt
unitypy-1.24.2.dist-info/top_level.txt
unitypy-1.24.2.dist-info/RECORD
unitypy-1.24.2.dist-info/licenses/LICENSE
unitypy-1.24.2.dist-info/sboms/auditwheel.cdx.json
