Metadata-Version: 2.4
Name: UnityPy
Version: 1.24.2
Summary: A Unity extraction and patching package
Author-email: Rudolf Kolbe <rkolbe96@gmail.com>
License: MIT License
Project-URL: Homepage, https://github.com/K0lb3/UnityPy
Project-URL: Bug Tracker, https://github.com/K0lb3/UnityPy/issues
Keywords: python,unity,unity-asset,python3,data-mining,unitypack,assetstudio,unity-asset-extractor
Classifier: License :: OSI Approved :: MIT License
Classifier: Operating System :: OS Independent
Classifier: Intended Audience :: Developers
Classifier: Development Status :: 5 - Production/Stable
Classifier: Programming Language :: Python
Classifier: Programming Language :: Python :: 3
Classifier: Programming Language :: Python :: 3.8
Classifier: Programming Language :: Python :: 3.9
Classifier: Programming Language :: Python :: 3.10
Classifier: Programming Language :: Python :: 3.11
Classifier: Programming Language :: Python :: 3.12
Classifier: Programming Language :: Python :: 3.13
Classifier: Programming Language :: Python :: 3.14
Classifier: Topic :: Software Development :: Libraries :: Python Modules
Classifier: Topic :: Games/Entertainment
Classifier: Topic :: Multimedia :: Graphics
Requires-Python: >=3.8
License-File: LICENSE
Requires-Dist: lz4
Requires-Dist: brotli
Requires-Dist: Pillow
Requires-Dist: texture2ddecoder>=1.0.5
Requires-Dist: etcpak
Requires-Dist: astc-encoder-py>=0.1.12
Requires-Dist: fmod_toolkit
Requires-Dist: fsspec
Requires-Dist: attrs
Provides-Extra: ttgen
Requires-Dist: typetreegeneratorapi>=0.0.10; extra == "ttgen"
Provides-Extra: full
Requires-Dist: unitypy[ttgen]; extra == "full"
Provides-Extra: tests
Requires-Dist: pytest; extra == "tests"
Requires-Dist: pillow; extra == "tests"
Requires-Dist: psutil; extra == "tests"
Requires-Dist: unitypy[full]; extra == "tests"
Provides-Extra: dev
Requires-Dist: ruff; extra == "dev"
Requires-Dist: unitypy[tests]; extra == "dev"
Dynamic: license-file
